metrician/__init__.py
metrician/constants.py
metrician/interface.py
metrician/configs/__init__.py
metrician/configs/cfg.py
metrician/configs/defaults.py
metrician/configs/interface.py
metrician/dataset/__init__.py
metrician/explainations/__init__.py
metrician/explainations/image.py
metrician/explainations/interface.py
metrician/explainations/tabular.py
metrician/explainations/tests.py
metrician/explainations/text.py
metrician/monitors/OOD.py
metrician/monitors/Variance.py
metrician/monitors/__init__.py
metrician/monitors/interface.py
metrician/monitors/tests.py
metrician/recorders/__init__.py
metrician/recorders/bert.py
metrician/recorders/distribution.py
metrician/recorders/interface.py
metrician/recorders/outliers.py
metrician/recorders/topk.py
metrician/signals/__init__.py
metrician/signals/interface.py
metrician/signals/loss.py
metrician/signals/outliers.py
metrician/signals/roc.py
metrician/signals/tests.py
metrician/writers/__init__.py
metrician/writers/interface.py
metrician/writers/writer.py
metrician-0.0.3.dist-info/LICENSE
metrician-0.0.3.dist-info/METADATA
metrician-0.0.3.dist-info/WHEEL
metrician-0.0.3.dist-info/top_level.txt
metrician-0.0.3.dist-info/RECORD
